SimpleQt/__init__.py
SimpleQt/box.py
SimpleQt/buttons.py
SimpleQt/mainwindow.py
SimpleQt/menuitems.py
SimpleQt/settings.py
SimpleQt/toolbar.py
SimpleQt/trayicon.py
SimpleQt/widgets.py
SimpleQt/dialogs/__init__.py
SimpleQt/dialogs/settings.py
SimpleQt-1.0.0.dist-info/AUTHORS
SimpleQt-1.0.0.dist-info/COPYING
SimpleQt-1.0.0.dist-info/METADATA
SimpleQt-1.0.0.dist-info/WHEEL
SimpleQt-1.0.0.dist-info/top_level.txt
SimpleQt-1.0.0.dist-info/RECORD
